Design/WR_CONTRL.v
module WR_CONTRL #(parameter ADDR_WIDTH = 4)(
    input wire w_clk,w_rst,
    //interface
    input wire winc,
    output wire wfull,
    //pointers 
    output wire  [ADDR_WIDTH:0] w_ptr,
    input wire [ADDR_WIDTH:0] r_ptr,
    //memory
    output wire [ADDR_WIDTH-1:0] waddr
);
    //Registers
    reg [ADDR_WIDTH:0] gray_ptr,bn_ptr;
    reg full_flag;

    // Binary Encoded Pointer Logic
    always @(posedge w_clk or negedge w_rst) begin
        if (!w_rst) begin
            bn_ptr <= 'b0;
        end else begin
            if(winc & ~(full_flag))begin
                bn_ptr <= bn_ptr + 'd1;
            end
        end
    end

    // Gray Encoded Pointer Logic
    integer i; 
    always @(posedge w_clk or negedge w_rst) begin
        if (!w_rst) begin
            gray_ptr <= 'b0;
        end else begin
            for (i=0; i<ADDR_WIDTH-1; i=i+1) begin
            gray_ptr[i] = bn_ptr[i] ^ bn_ptr[i+1];
            end 
            gray_ptr[ADDR_WIDTH] = bn_ptr[ADDR_WIDTH];
        end
    end
    
    // Full Flag Logic
    wire full_condition;
    assign full_condition = (gray_ptr[ADDR_WIDTH:ADDR_WIDTH-1] != r_ptr[ADDR_WIDTH:ADDR_WIDTH-1])&& (gray_ptr[ADDR_WIDTH-2:0] == r_ptr[ADDR_WIDTH-2:0]);
    always @(posedge w_clk or negedge w_rst) begin
        if (!w_rst) begin
            full_flag <= 1'b0;
        end else begin
            if (full_condition) begin
                full_flag <= 1'b1;
            end else begin
                full_flag <= 1'b0;
            end
        end
    end
    //Outputs
    assign waddr = bn_ptr[ADDR_WIDTH-1:0];
    assign w_ptr = gray_ptr;
    assign wfull = full_flag;

endmodule

Design/RD_CONTRL.v
module RD_CONTRL #(parameter ADDR_WIDTH = 4)(
    input wire r_clk,r_rst,
    //interface
    input wire rinc,
    output wire rempty,
    //pointers 
    input wire  [ADDR_WIDTH:0] w_ptr,
    output wire [ADDR_WIDTH:0] r_ptr,
    //memory
    output wire [ADDR_WIDTH-1:0] raddr
);

    //Registers
    reg [ADDR_WIDTH:0] gray_ptr,bn_ptr;
    reg empty_flag;

    // Binary Encoded Pointer Logic
    always @(posedge r_clk or negedge r_rst) begin
        if (!r_rst) begin
            bn_ptr <= 'b0;
        end else begin
            if(rinc & ~(empty_flag))begin
                bn_ptr <= bn_ptr + 'd1;
            end
        end
    end

    // Gray Encoded Pointer Logic
    integer i; 
    always @(posedge r_clk or negedge r_rst) begin
        if (!r_rst) begin
            gray_ptr <= 'b0;
        end else begin
            for (i=0; i<ADDR_WIDTH-1; i=i+1) begin
            gray_ptr[i] = bn_ptr[i] ^ bn_ptr[i+1];
            end 
            gray_ptr[ADDR_WIDTH] = bn_ptr[ADDR_WIDTH];
        end
    end
    
    // Full Flag Logic
    wire empty_condition;
    assign empty_condition = (gray_ptr == w_ptr);
    always @(posedge r_clk or negedge r_rst) begin
        if (!r_rst) begin
            empty_flag <= 1'b1;
        end else begin
            if (empty_condition) begin
                empty_flag <= 1'b1;
            end else begin
                empty_flag <= 1'b0;
            end
        end
    end
    //Outputs
    assign raddr = bn_ptr[ADDR_WIDTH-1:0];
    assign r_ptr = gray_ptr;
    assign rempty = empty_flag;

endmodule

Design/DATA_SYNC.v
module DATA_SYNC #(parameter NUM_STAGES = 2 ,parameter BUS_WIDTH = 8)(
    input wire CLK,RST,
    input wire [BUS_WIDTH-1:0] Unsync_bus,
    output wire [BUS_WIDTH-1:0] sync_bus
);

// Using Flip Flop synchronizer with Gray encoding input/output 
    reg [BUS_WIDTH-1:0] synchronizer [NUM_STAGES-1:0] ;
    integer i;

    always @(posedge CLK or negedge RST ) begin
        if (!RST) begin
            for (i = 0; i <= NUM_STAGES-1; i=i+1 ) begin
               synchronizer[i] <= 'b0; 
            end 
        end else begin
            synchronizer[0] <= Unsync_bus;
            for (i = 1; i<= NUM_STAGES-1; i=i+1) begin
                synchronizer[i] <= synchronizer[i-1];
           end
        end
    end

    assign sync_bus = synchronizer[NUM_STAGES-1];
endmodule

Design/FIFO_RAM.v
module DUAL_RAM #(parameter DATA_WIDTH =8,parameter ADDR_WIDTH= 4 ,parameter MEM_SIZE = 32)(
    //Write Part
    input wire w_clk,w_rst,
    input wire wclken,
    input wire [DATA_WIDTH-1:0] wrdata,
    input wire [ADDR_WIDTH-1:0] waddr, 
    //Read Part
    output reg [DATA_WIDTH-1:0] rdata,
    input wire  [ADDR_WIDTH-1:0] raddr
);

// RAM Structure
    reg [ADDR_WIDTH-1:0] MEM [MEM_SIZE-1:0];
    integer i;

// Clock gating
    wire g_clk;
    reg g_clk_latch;
    always @(w_clk or wclken) begin
        if(!w_clk)begin
            g_clk_latch <= wclken;
        end
    end
    assign g_clk = w_clk & g_clk_latch;

// Memory Logic
    always @(posedge g_clk or negedge w_rst) begin
        if (!w_rst) begin
            for (i=0; i<= MEM_SIZE-1; i=i+1) begin
                MEM[i] <= 'b0;
            end
            rdata <= 'b0;
        end else begin
            //Read Part logic
                rdata <= MEM[raddr];
            //Write Part logic   
                MEM[waddr] <= wrdata;
        end
    end    

endmodule

Design/FIFO.v
module FIFO #(parameter DATA_WIDTH = 8 ,parameter ADDR_WIDTH = 4,parameter MEM_SIZE = 32)(
    //Write Part
    input wire W_CLK,W_RST,
    input wire W_INC,
    input wire [DATA_WIDTH-1:0] WR_DATA,
    output wire FULL,
    //Read Part
    input wire R_CLK,R_RST,
    input wire R_INC,
    output wire [DATA_WIDTH-1:0] RD_DATA,
    output wire EMPTY
);
//Parameters
    //Synchronizer steps "The output is at the second Clock"
    parameter NUM_STAGES = 2;

//Wires
    //Address
        wire [ADDR_WIDTH-1:0] Wr_ADDR;
        wire [ADDR_WIDTH-1:0] Rd_ADDR;
    //Read Pointers
        wire [ADDR_WIDTH:0] unsync_rd_ptr;
        wire [ADDR_WIDTH:0] sync_rd_ptr;
    //Write Pointers
        wire [ADDR_WIDTH:0] unsync_wr_ptr;
        wire [ADDR_WIDTH:0] sync_wr_ptr;
    //Write Clock Enable
        wire Wr_CLK_En;
        assign Wr_CLK_En = ~(FULL) & W_INC;

//FIFO MEMORY
DUAL_RAM #(.DATA_WIDTH(DATA_WIDTH),.ADDR_WIDTH(ADDR_WIDTH),.MEM_SIZE(MEM_SIZE)) FIFO_MEMORY(
    //Write Part
    .w_clk(W_CLK),.w_rst(W_RST),
    .wrdata(WR_DATA),
    .waddr(Wr_ADDR),
    .wclken(Wr_CLK_En),
    //Read Part
    .rdata(RD_DATA),
    .raddr(Rd_ADDR)
);

//SYNCING READ TO WRITE 
DATA_SYNC #(.NUM_STAGES(NUM_STAGES),.BUS_WIDTH(DATA_WIDTH)) SYNC_R2W(
    .CLK(W_CLK),.RST(W_RST),
    .Unsync_bus(unsync_rd_ptr),
    .sync_bus(sync_rd_ptr),
);

//SYNCING WRITE TO READ
DATA_SYNC #(.NUM_STAGES(NUM_STAGES),.BUS_WIDTH(DATA_WIDTH)) SYNC_W2R(
    .CLK(R_CLK),.RST(R_RST),
    .Unsync_bus(unsync_wr_ptr),
    .sync_bus(sync_wr_ptr),
);

//READ CONTROL LOGIC
RD_CONTRL #(.ADDR_WIDTH(ADDR_WIDTH)) rptr_empty(
    .r_clk(R_CLK),.r_rst(R_RST),
    //interface
    .rinc(R_INC),
    .rempty(EMPTY),
    //pointers 
    .w_ptr(sync_wr_ptr),
    .r_ptr(unsync_rd_ptr),
    //memory
    .raddr(Rd_ADDR)
);

//WRITE CONTROL LOGIC
WR_CONTRL #(.ADDR_WIDTH(ADDR_WIDTH)) wptr_full(
    .w_clk(W_CLK),.w_rst(W_RST),
    //interface
    .winc(W_INC),
    .wfull(FULL),
    //pointers 
    .w_ptr(unsync_wr_ptr),
    .r_ptr(sync_rd_ptr),
    //memory
    .waddr(Wr_ADDR)
);

endmodule

Testbench/Testbench.sv
/*
    First the FIFO Problem:
        Reading Frequency = 40 MHz  "Reading Period = 25ns"
        Writing Frequency = 100 MHz "Writing Period = 10ns"
        Writing Data Packet size = 10 Byte
    Solution:     
        Time needed to write One Byte = 10ns
        Time needed to write the Packet = 100 ns
        number of packets to be read = 100/25 = 4 byte 
        then min FIFO Depth = 10 - 4 = 6 byte 
*/
`timescale 1ns/1ps

module tb_FIFO;
//////////////////////////////
////////// Signals //////////
////////////////////////////
//Parameters
    parameter DATA_WIDTH = 8 ;
    parameter ADDR_WIDTH = 4;
    parameter MEM_SIZE = 32;

//Write Part
    reg tb_W_CLK,tb_W_RST;
    reg tb_W_INC;
    reg [DATA_WIDTH-1:0] tb_WR_DATA;
    wire tb_FULL;

//Read Part
    reg tb_R_CLK,tb_R_RST;
    reg tb_R_INC;
    wire [DATA_WIDTH-1:0] tb_RD_DATA;
    wire tb_EMPTY;

//////////////////////////////
/////// Instatiation ////////
////////////////////////////

FIFO #(.DATA_WIDTH(DATA_WIDTH),.ADDR_WIDTH(ADDR_WIDTH),.MEM_SIZE(MEM_SIZE)) DUT(
    //Write Part
    .W_CLK(tb_W_CLK),
    .W_RST(tb_W_RST),
    .W_INC(tb_W_INC),
    .WR_DATA(tb_WR_DATA),
    .FULL(tb_FULL),
    //Read Part
    .R_CLK(tb_R_CLK),
    .R_RST(tb_R_RST),
    .R_INC(tb_R_INC),
    .RD_DATA(tb_RD_DATA),
    .EMPTY(tb_EMPTY)
);

//////////////////////////////
///// Clock Generation //////
////////////////////////////
    localparam RD_Clock_Period = 25;
    always #(RD_Clock_Period/2) tb_R_CLK=~tb_R_CLK;
    initial tb_R_CLK = 1'b1;

    localparam WR_Clock_Period = 10;
    always #(WR_Clock_Period/2) tb_W_CLK=~tb_W_CLK;
    initial tb_W_CLK = 1'b1;
    
//////////////////////////////
//// Write Initial Block ////
////////////////////////////
    initial begin
        //Start the Testbench
        $display("======= Testbench Starts =======");
        $dumpfile("tb_results.vcd");
        $dumpvars;

        // Write Initialization

        // Reset Test
        
        // Write a Packet

    end

//////////////////////////////
///// Read Initial Block ////
////////////////////////////
    initial begin
        //Read Initialization

        //Reset Test

        //Read a Packet
        
        //stop the Testbench
        $display("======= Testbench End =======");
        #1000; $stop;   
    end

//////////////////////////////
////////// Tasks ////////////
////////////////////////////
    
endmodule

Simulation/tb_results.vcd
$date
	Fri Aug  9 03:57:19 2024
$end
$version
	QuestaSim Version 2021.1
$end
$timescale
	1ps
$end

$scope module tb_FIFO $end
$var parameter 32 ! DATA_WIDTH $end
$var parameter 32 " ADDR_WIDTH $end
$var parameter 32 # MEM_SIZE $end
$var parameter 32 $ RD_Clock_Period $end
$var parameter 32 % WR_Clock_Period $end
$var reg 1 & tb_W_CLK $end
$var reg 1 ' tb_W_RST $end
$var reg 1 ( tb_W_INC $end
$var reg 8 ) tb_WR_DATA [7:0] $end
$var wire 1 * tb_FULL $end
$var reg 1 + tb_R_CLK $end
$var reg 1 , tb_R_RST $end
$var reg 1 - tb_R_INC $end
$var wire 1 . tb_RD_DATA [7] $end
$var wire 1 / tb_RD_DATA [6] $end
$var wire 1 0 tb_RD_DATA [5] $end
$var wire 1 1 tb_RD_DATA [4] $end
$var wire 1 2 tb_RD_DATA [3] $end
$var wire 1 3 tb_RD_DATA [2] $end
$var wire 1 4 tb_RD_DATA [1] $end
$var wire 1 5 tb_RD_DATA [0] $end
$var wire 1 6 tb_EMPTY $end

$scope task Write_Initialization $end
$upscope $end

$scope task Write_Reset $end
$upscope $end

$scope task Read_Initialization $end
$upscope $end

$scope task Read_Reset $end
$upscope $end

$scope module DUT $end
$var parameter 32 7 DATA_WIDTH $end
$var parameter 32 8 ADDR_WIDTH $end
$var parameter 32 9 MEM_SIZE $end
$var parameter 32 : NUM_STAGES $end
$var wire 1 ; W_CLK $end
$var wire 1 < W_RST $end
$var wire 1 = W_INC $end
$var wire 1 > WR_DATA [7] $end
$var wire 1 ? WR_DATA [6] $end
$var wire 1 @ WR_DATA [5] $end
$var wire 1 A WR_DATA [4] $end
$var wire 1 B WR_DATA [3] $end
$var wire 1 C WR_DATA [2] $end
$var wire 1 D WR_DATA [1] $end
$var wire 1 E WR_DATA [0] $end
$var wire 1 * FULL $end
$var wire 1 F R_CLK $end
$var wire 1 G R_RST $end
$var wire 1 H R_INC $end
$var wire 1 . RD_DATA [7] $end
$var wire 1 / RD_DATA [6] $end
$var wire 1 0 RD_DATA [5] $end
$var wire 1 1 RD_DATA [4] $end
$var wire 1 2 RD_DATA [3] $end
$var wire 1 3 RD_DATA [2] $end
$var wire 1 4 RD_DATA [1] $end
$var wire 1 5 RD_DATA [0] $end
$var wire 1 6 EMPTY $end
$var wire 1 I Wr_ADDR [3] $end
$var wire 1 J Wr_ADDR [2] $end
$var wire 1 K Wr_ADDR [1] $end
$var wire 1 L Wr_ADDR [0] $end
$var wire 1 M Rd_ADDR [3] $end
$var wire 1 N Rd_ADDR [2] $end
$var wire 1 O Rd_ADDR [1] $end
$var wire 1 P Rd_ADDR [0] $end
$var wire 1 Q unsync_rd_ptr [4] $end
$var wire 1 R unsync_rd_ptr [3] $end
$var wire 1 S unsync_rd_ptr [2] $end
$var wire 1 T unsync_rd_ptr [1] $end
$var wire 1 U unsync_rd_ptr [0] $end
$var wire 1 V sync_rd_ptr [4] $end
$var wire 1 W sync_rd_ptr [3] $end
$var wire 1 X sync_rd_ptr [2] $end
$var wire 1 Y sync_rd_ptr [1] $end
$var wire 1 Z sync_rd_ptr [0] $end
$var wire 1 [ unsync_wr_ptr [4] $end
$var wire 1 \ unsync_wr_ptr [3] $end
$var wire 1 ] unsync_wr_ptr [2] $end
$var wire 1 ^ unsync_wr_ptr [1] $end
$var wire 1 _ unsync_wr_ptr [0] $end
$var wire 1 ` sync_wr_ptr [4] $end
$var wire 1 a sync_wr_ptr [3] $end
$var wire 1 b sync_wr_ptr [2] $end
$var wire 1 c sync_wr_ptr [1] $end
$var wire 1 d sync_wr_ptr [0] $end
$var wire 1 e Wr_CLK_En $end

$scope module FIFO_MEMORY $end
$var parameter 32 f DATA_WIDTH $end
$var parameter 32 g ADDR_WIDTH $end
$var parameter 32 h MEM_SIZE $end
$var wire 1 ; w_clk $end
$var wire 1 < w_rst $end
$var wire 1 e wclken $end
$var wire 1 > wrdata [7] $end
$var wire 1 ? wrdata [6] $end
$var wire 1 @ wrdata [5] $end
$var wire 1 A wrdata [4] $end
$var wire 1 B wrdata [3] $end
$var wire 1 C wrdata [2] $end
$var wire 1 D wrdata [1] $end
$var wire 1 E wrdata [0] $end
$var wire 1 I waddr [3] $end
$var wire 1 J waddr [2] $end
$var wire 1 K waddr [1] $end
$var wire 1 L waddr [0] $end
$var reg 8 i rdata [7:0] $end
$var wire 1 M raddr [3] $end
$var wire 1 N raddr [2] $end
$var wire 1 O raddr [1] $end
$var wire 1 P raddr [0] $end
$var integer 32 j i $end
$var wire 1 k g_clk $end
$var reg 1 l g_clk_latch $end
$upscope $end

$scope module SYNC_R2W $end
$var parameter 32 m NUM_STAGES $end
$var parameter 32 n BUS_WIDTH $end
$var wire 1 ; CLK $end
$var wire 1 < RST $end
$var wire 1 Q Unsync_bus [4] $end
$var wire 1 R Unsync_bus [3] $end
$var wire 1 S Unsync_bus [2] $end
$var wire 1 T Unsync_bus [1] $end
$var wire 1 U Unsync_bus [0] $end
$var wire 1 V sync_bus [4] $end
$var wire 1 W sync_bus [3] $end
$var wire 1 X sync_bus [2] $end
$var wire 1 Y sync_bus [1] $end
$var wire 1 Z sync_bus [0] $end
$var integer 32 o i $end
$upscope $end

$scope module SYNC_W2R $end
$var parameter 32 p NUM_STAGES $end
$var parameter 32 q BUS_WIDTH $end
$var wire 1 F CLK $end
$var wire 1 G RST $end
$var wire 1 [ Unsync_bus [4] $end
$var wire 1 \ Unsync_bus [3] $end
$var wire 1 ] Unsync_bus [2] $end
$var wire 1 ^ Unsync_bus [1] $end
$var wire 1 _ Unsync_bus [0] $end
$var wire 1 ` sync_bus [4] $end
$var wire 1 a sync_bus [3] $end
$var wire 1 b sync_bus [2] $end
$var wire 1 c sync_bus [1] $end
$var wire 1 d sync_bus [0] $end
$var integer 32 r i $end
$upscope $end

$scope module rptr_empty $end
$var parameter 32 s ADDR_WIDTH $end
$var wire 1 F r_clk $end
$var wire 1 G r_rst $end
$var wire 1 H rinc $end
$var wire 1 6 rempty $end
$var wire 1 ` w_ptr [4] $end
$var wire 1 a w_ptr [3] $end
$var wire 1 b w_ptr [2] $end
$var wire 1 c w_ptr [1] $end
$var wire 1 d w_ptr [0] $end
$var wire 1 Q r_ptr [4] $end
$var wire 1 R r_ptr [3] $end
$var wire 1 S r_ptr [2] $end
$var wire 1 T r_ptr [1] $end
$var wire 1 U r_ptr [0] $end
$var wire 1 M raddr [3] $end
$var wire 1 N raddr [2] $end
$var wire 1 O raddr [1] $end
$var wire 1 P raddr [0] $end
$var reg 5 t gray_ptr [4:0] $end
$var reg 5 u bn_ptr [4:0] $end
$var reg 1 v empty_flag $end
$var integer 32 w i $end
$var wire 1 x empty_condition $end
$upscope $end

$scope module wptr_full $end
$var parameter 32 y ADDR_WIDTH $end
$var wire 1 ; w_clk $end
$var wire 1 < w_rst $end
$var wire 1 = winc $end
$var wire 1 * wfull $end
$var wire 1 [ w_ptr [4] $end
$var wire 1 \ w_ptr [3] $end
$var wire 1 ] w_ptr [2] $end
$var wire 1 ^ w_ptr [1] $end
$var wire 1 _ w_ptr [0] $end
$var wire 1 V r_ptr [4] $end
$var wire 1 W r_ptr [3] $end
$var wire 1 X r_ptr [2] $end
$var wire 1 Y r_ptr [1] $end
$var wire 1 Z r_ptr [0] $end
$var wire 1 I waddr [3] $end
$var wire 1 J waddr [2] $end
$var wire 1 K waddr [1] $end
$var wire 1 L waddr [0] $end
$var reg 5 z gray_ptr [4:0] $end
$var reg 5 { bn_ptr [4:0] $end
$var reg 1 | full_flag $end
$var integer 32 } i $end
$var wire 1 ~ full_condition $end
$upscope $end
$upscope $end
$upscope $end

$scope begin std $end
$upscope $end
$enddefinitions $end
#0
$dumpvars
1&
1'
0(
b0 )
1+
1,
0-
bx i
xl
bx t
bx u
0v
bx z
bx {
0|
b1000 !
b100 "
b100000 #
b11001 $
b1010 %
b1000 7
b100 8
b100000 9
b10 :
b1000 f
b100 g
b100000 h
b10 m
b101 n
b10 p
b101 q
b100 s
b100 y
bx j
b10 o
b10 r
b11 w
b11 }
0*
x5
x4
x3
x2
x1
x0
x/
x.
06
xL
xK
xJ
xI
xP
xO
xN
xM
xU
xT
xS
xR
xQ
xZ
xY
xX
xW
xV
x_
x^
x]
x\
x[
xd
xc
xb
xa
x`
0e
xk
xx
x~
0H
1G
1F
0E
0D
0C
0B
0A
0@
0?
0>
0=
1<
1;
$end
#5000
0&
0;
0k
0l
#10000
0'
1&
0<
1;
b0 o
b1 o
b10 o
b0 j
b1 j
b10 j
b11 j
b100 j
b101 j
b110 j
b111 j
b1000 j
b1001 j
b1010 j
b1011 j
b1100 j
b1101 j
b1110 j
b1111 j
b10000 j
b10001 j
b10010 j
b10011 j
b10100 j
b10101 j
b10110 j
b10111 j
b11000 j
b11001 j
b11010 j
b11011 j
b11100 j
b11101 j
b11110 j
b11111 j
b100000 j
b0 {
b0 z
b0 i
05
04
03
02
01
00
0/
0.
0_
0^
0]
0\
0[
0L
0K
0J
0I
0Z
0Y
0X
0W
0V
0~
#12000
0+
0F
#15000
0&
0;
#20000
1'
1&
1<
1;
b0 }
b1 }
b10 }
b11 }
b1 o
b10 o
#24000
1+
1F
b1 r
b10 r
b0 w
b1 w
b10 w
b11 w
#25000
0,
0&
0G
0;
b0 r
b1 r
b10 r
b0 u
b0 t
1v
0U
0T
0S
0R
0Q
0P
0O
0N
0M
0d
0c
0b
0a
0`
16
1x
#30000
1&
1;
b1 o
b10 o
xZ
xY
xX
xW
xV
x~
#35000
0&
0;
#36000
0+
0F
#40000
1&
1;
b1 o
b10 o
0Z
0Y
0X
0W
0V
0~
#45000
0&
0;
#48000
1+
1F
b0 r
b1 r
b10 r
#50000
1,
1&
1G
1;
b1 o
b10 o
#55000
0&
0;
#60000
0+
1&
0F
1;
#65000
0&
0;
#70000
1&
1;
#72000
1+
1F
b1 r
b10 r
b0 w
b1 w
b10 w
b11 w
